Workbook

Sheet Cover
B3: DCF Model- Individual Assignment
B8: Submitted to - Prof. Pulin Aggarwal
B10: Submitted by - Pushp (25PGDM155)
B13: Video Link -
B15: https://drive.google.com/file/d/1k_QBqPZNkdEYOCHSCVSIDzXzKsG8dEGS/view?usp=sharing

Sheet Assumptions
A1: VoltDrive Motors - Assumptions
B2: Value | C2: FY2026E | D2: FY2027E | E2: FY2028E | F2: FY2029E | G2: FY2030E
A3: Cost of Capital & Valuation Assumptions
A4: Risk-Free Rate (Rf) | B4: 0.0425
A5: Levered Beta | B5: 1.85
A6: Equity Market Risk Premium (Rm – Rf) | B6: 0.055
A7: Pre-tax Cost of Debt (Kd) | B7: 0.075
A8: Marginal Tax Rate (t) | B8: 0.21
A9: Diluted Shares Outstanding (mm) | B9: 400
A10: Reference Share Price ($) | B10: 8.9
A11: Terminal Growth Rate (g) | B11: 0.025
A12: Volume & Pricing Drivers
A13: Unit Growth % (Vehicles Sold) | C13: 0.12 | D13: 0.25 | E13: 0.35 | F13: 0.28 | G13: 0.18
A14: ASP Anchor ($'000/unit) — FY2027E & FY2030E given; FY26E/28E/29E interpolated straight-line | D14: 68 | G14: 55
A15: Other Revenue (% of Vehicle Sales Revenue) | B15: 0.02
A16: Unit Cost Drivers
A17: Battery Cost per Unit ($'000) | B17: 21 | C17: 18.5 | D17: 15.8 | E17: 13.2 | F17: 11.5 | G17: 10.2
A18: Other Materials/Assembly Cost per Unit ($'000) | B18: 45 | C18: 42 | D18: 38.5 | E18: 34 | F18: 30.5 | G18: 28
A19: Operating Expense Ratios (% of Revenue)
A20: R&D as % of Revenue | C20: 0.14 | D20: 0.115 | E20: 0.09 | F20: 0.075 | G20: 0.065
A21: SG&A as % of Revenue | C21: 0.15 | D21: 0.125 | E21: 0.105 | F21: 0.09 | G21: 0.08
A22: Capacity & Capex Assumptions
A23: FY2025A Installed Capacity, Beginning (units, '000) | B23: 100
A24: Utilization Target % (anchors FY26E & FY30E; FY27E-29E interpolated) | C24: 0.65 | G24: 0.9
A25: Capex per Unit of New Capacity ($mm per '000 units) | B25: 12
A26: Maintenance Capex (% of Revenue) (anchors FY26E & FY30E; interpolated) | C26: 0.035 | G26: 0.025
A27: Debt & Financing Assumptions
A28: ST Debt Draws ($mm) | B28: 0
A29: ST Debt Repayments ($mm) | B29: 0
A30: New LT Debt (% of Total Capex) | B30: 0.5
A31: Scheduled LT Repayment (% of Beginning LT Balance) | B31: 0.05
A32: Minimum Cash Balance ($mm) | B32: 400

Sheet Income Statement
A1: VoltDrive Motors - EV Automobile Manufacturer
A2: Income Statement ($ in millions)
B3: FY2024A | C3: FY2025A | D3: FY2026E | E3: FY2027E | F3: FY2028E | G3: FY2029E | H3: FY2030E
A5: Revenue | B5: 3000 | C5: 4500 | D5: ='Revenue & Cost Drivers'!C11 -> 4835.6757 | E5: ='Revenue & Cost Drivers'!D11 -> 5789.1892 | F5: ='Revenue & Cost Drivers'!E11 -> 7317.3649 | G5: ='Revenue & Cost Drivers'!F11 -> 8728.7351 | H5: ='Revenue & Cost Drivers'!G11 -> 9547.667
A6: Revenue Growth % | C6: =(C5-B5)/B5 -> 0.5 | D6: =(D5-C5)/C5 -> 0.074594595 | E6: =(E5-D5)/D5 -> 0.1971831 | F6: =(F5-E5)/E5 -> 0.26397059 | G6: =(G5-F5)/F5 -> 0.19287958 | H6: =(H5-G5)/G5 -> 0.093820225
A7: Cost of Goods Sold | B7: 2400 | C7: 3375 | D7: ='Revenue & Cost Drivers'!C16 -> 4039.7456 | E7: ='Revenue & Cost Drivers'!D16 -> 4532.194 | F7: ='Revenue & Cost Drivers'!E16 -> 5318.442 | G7: ='Revenue & Cost Drivers'!F16 -> 6057.6153 | H7: ='Revenue & Cost Drivers'!G16 -> 6501.2635
A8: Gross Profit | B8: =B5-B7 -> 600 | C8: =C5-C7 -> 1125 | D8: =D5-D7 -> 795.93005 | E8: =E5-E7 -> 1256.9952 | F8: =F5-F7 -> 1998.9229 | G8: =G5-G7 -> 2671.1199 | H8: =H5-H7 -> 3046.4036
A9: R&D Expense | B9: 300 | C9: 360 | D9: ='Revenue & Cost Drivers'!C19 -> 676.99459 | E9: ='Revenue & Cost Drivers'!D19 -> 665.75676 | F9: ='Revenue & Cost Drivers'!E19 -> 658.56284 | G9: ='Revenue & Cost Drivers'!F19 -> 654.65514 | H9: ='Revenue & Cost Drivers'!G19 -> 620.59836
A10: SG&A Expense | B10: 360 | C10: 450 | D10: ='Revenue & Cost Drivers'!C21 -> 725.35135 | E10: ='Revenue & Cost Drivers'!D21 -> 723.64865 | F10: ='Revenue & Cost Drivers'!E21 -> 768.32331 | G10: ='Revenue & Cost Drivers'!F21 -> 785.58616 | H10: ='Revenue & Cost Drivers'!G21 -> 763.81336
A11: EBITDA | B11: =B8-B9-B10 -> -60 | C11: =C8-C9-C10 -> 315 | D11: =D8-D9-D10 -> -606.4159 | E11: =E8-E9-E10 -> -132.41017 | F11: =F8-F9-F10 -> 572.03674 | G11: =G8-G9-G10 -> 1230.8786 | H11: =H8-H9-H10 -> 1661.9918
A12: Depreciation & Amortization | B12: 150 | C12: 200 | D12: ='Capacity Expansion'!C23 -> 227.42857 | E12: ='Capacity Expansion'!D23 -> 225.48922 | F12: ='Capacity Expansion'!E23 -> 235.82626 | G12: ='Capacity Expansion'!F23 -> 260.40983 | H12: ='Capacity Expansion'!G23 -> 283.38045
A13: EBIT | B13: =B11-B12 -> -210 | C13: =C11-C12 -> 115 | D13: =D11-D12 -> -833.84447 | E13: =E11-E12 -> -357.8994 | F13: =F11-F12 -> 336.21049 | G13: =G11-G12 -> 970.46874 | H13: =H11-H12 -> 1378.6114
A14: Interest Expense | B14: 75 | C14: 85 | D14: ='Debt Schedule'!C20 -> 155.25 | E14: ='Debt Schedule'!D20 -> 155.77405 | F14: ='Debt Schedule'!E20 -> 162.24145 | G14: ='Debt Schedule'!F20 -> 175.78509 | H14: ='Debt Schedule'!G20 -> 188.77956
A15: EBT (Pre-tax Income) | B15: =B13-B14 -> -285 | C15: =C13-C14 -> 30 | D15: =D13-D14 -> -989.09447 | E15: =E13-E14 -> -513.67344 | F15: =F13-F14 -> 173.96904 | G15: =G13-G14 -> 794.68365 | H15: =H13-H14 -> 1189.8318
A16: Tax Expense | B16: 0 | C16: 7.5 | D16: =IF(D15>0,D15*WACC!$B$11,0) -> 0 | E16: =IF(E15>0,E15*WACC!$B$11,0) -> 0 | F16: =IF(F15>0,F15*WACC!$B$11,0) -> 36.533498 | G16: =IF(G15>0,G15*WACC!$B$11,0) -> 166.88357 | H16: =IF(H15>0,H15*WACC!$B$11,0) -> 249.86469
A17: Net Income | B17: =B15-B16 -> -285 | C17: =C15-C16 -> 22.5 | D17: =D15-D16 -> -989.09447 | E17: =E15-E16 -> -513.67344 | F17: =F15-F16 -> 137.43554 | G17: =G15-G16 -> 627.80008 | H17: =H15-H16 -> 939.96715
A19: Gross Margin % | B19: =B8/B5 -> 0.2 | C19: =C8/C5 -> 0.25 | D19: =D8/D5 -> 0.16459542 | E19: =E8/E5 -> 0.21712803 | F19: =F8/F5 -> 0.27317524 | G19: =G8/G5 -> 0.30601454 | H19: =H8/H5 -> 0.31907308
A20: EBITDA Margin % | B20: =B11/B5 -> -0.02 | C20: =C11/C5 -> 0.07 | D20: =D11/D5 -> -0.12540458 | E20: =E11/E5 -> -0.022871972 | F20: =F11/F5 -> 0.078175239 | G20: =G11/G5 -> 0.14101454 | H20: =H11/H5 -> 0.17407308
A21: Net Margin % | B21: =B17/B5 -> -0.095 | C21: =C17/C5 -> 0.005 | D21: =D17/D5 -> -0.20454111 | E21: =E17/E5 -> -0.088729773 | F21: =F17/F5 -> 0.018782108 | G21: =G17/G5 -> 0.071923374 | H21: =H17/H5 -> 0.09844993

Sheet Balance Sheet
A1: VoltDrive Motors - EV Automobile Manufacturer
A2: Balance Sheet ($ in millions)
B3: FY2024A | C3: FY2025A | D3: FY2026E | E3: FY2027E | F3: FY2028E | G3: FY2029E | H3: FY2030E
A4: Assets
A5: Cash & Equivalents | B5: 375 | C5: 482.5 | D5: ='Cash Flow Statement'!D24 -> 400 | E5: ='Cash Flow Statement'!E24 -> 400 | F5: ='Cash Flow Statement'!F24 -> 400 | G5: ='Cash Flow Statement'!G24 -> 728.8663 | H5: ='Cash Flow Statement'!H24 -> 1515.5569
A6: Accounts Receivable | B6: 300 | C6: 450 | D6: ='Income Statement'!D5*('Balance Sheet'!D24/365) -> 483.56757 | E6: ='Income Statement'!E5*('Balance Sheet'!E24/365) -> 578.91892 | F6: ='Income Statement'!F5*('Balance Sheet'!F24/365) -> 731.73649 | G6: ='Income Statement'!G5*('Balance Sheet'!G24/365) -> 872.87351 | H6: ='Income Statement'!H5*('Balance Sheet'!H24/365) -> 954.7667
A7: Inventory | B7: 450 | C7: 675 | D7: ='Income Statement'!D7*('Balance Sheet'!D25/365) -> 807.94913 | E7: ='Income Statement'!E7*('Balance Sheet'!E25/365) -> 906.43879 | F7: ='Income Statement'!F7*('Balance Sheet'!F25/365) -> 1063.6884 | G7: ='Income Statement'!G7*('Balance Sheet'!G25/365) -> 1211.5231 | H7: ='Income Statement'!H7*('Balance Sheet'!H25/365) -> 1300.2527
A8: Total Current Assets | B8: =SUM(B5:B7) -> 1125 | C8: =SUM(C5:C7) -> 1607.5 | D8: =SUM(D5:D7) -> 1691.5167 | E8: =SUM(E5:E7) -> 1885.3577 | F8: =SUM(F5:F7) -> 2195.4249 | G8: =SUM(G5:G7) -> 2813.2629 | H8: =SUM(H5:H7) -> 3770.5763
A9: Net PP&E (incl. Gigafactory) | B9: 2625 | C9: 2985 | D9: ='Capacity Expansion'!C24 -> 2959.546 | E9: ='Capacity Expansion'!D24 -> 3095.2196 | F9: ='Capacity Expansion'!E24 -> 3417.8791 | G9: ='Capacity Expansion'!F24 -> 3719.3684 | H9: ='Capacity Expansion'!G24 -> 3877.3177
A10: Total Assets | B10: =B8+B9 -> 3750 | C10: =C8+C9 -> 4592.5 | D10: =D8+D9 -> 4651.0627 | E10: =E8+E9 -> 4980.5773 | F10: =F8+F9 -> 5613.3039 | G10: =G8+G9 -> 6532.6313 | H10: =H8+H9 -> 7647.894
A11: Liabilities
A12: Accounts Payable | B12: 360 | C12: 540 | D12: ='Income Statement'!D7*('Balance Sheet'!D26/365) -> 646.3593 | E12: ='Income Statement'!E7*('Balance Sheet'!E26/365) -> 725.15103 | F12: ='Income Statement'!F7*('Balance Sheet'!F26/365) -> 850.95072 | G12: ='Income Statement'!G7*('Balance Sheet'!G26/365) -> 969.21844 | H12: ='Income Statement'!H7*('Balance Sheet'!H26/365) -> 1040.2022
A13: Short-term Debt | B13: 190 | C13: 190 | D13: ='Debt Schedule'!C8 -> 190 | E13: ='Debt Schedule'!D8 -> 190 | F13: ='Debt Schedule'!E8 -> 190 | G13: ='Debt Schedule'!F8 -> 190 | H13: ='Debt Schedule'!G8 -> 190
A14: Total Current Liabilities | B14: =SUM(B12:B13) -> 550 | C14: =SUM(C12:C13) -> 730 | D14: =SUM(D12:D13) -> 836.3593 | E14: =SUM(E12:E13) -> 915.15103 | F14: =SUM(F12:F13) -> 1040.9507 | G14: =SUM(G12:G13) -> 1159.2184 | H14: =SUM(H12:H13) -> 1230.2022
A15: Long-term Debt | B15: 1700 | C15: 1880 | D15: ='Debt Schedule'!C15 -> 1886.9873 | E15: ='Debt Schedule'!D15 -> 1973.2193 | F15: ='Debt Schedule'!E15 -> 2153.8012 | G15: ='Debt Schedule'!F15 -> 2327.0608 | H15: ='Debt Schedule'!G15 -> 2431.3726
A16: Total Liabilities | B16: =B14+B15 -> 2250 | C16: =C14+C15 -> 2610 | D16: =D14+D15 -> 2723.3466 | E16: =E14+E15 -> 2888.3704 | F16: =F14+F15 -> 3194.7519 | G16: =G14+G15 -> 3486.2792 | H16: =H14+H15 -> 3661.5747
A17: Equity
A18: Common Stock & APIC | B18: 1875 | C18: 2335 | D18: =C18+'Cash Flow Statement'!D19 -> 3269.3106 | E18: =D18+'Cash Flow Statement'!E19 -> 3947.4749 | F18: =E18+'Cash Flow Statement'!F19 -> 4136.3844 | G18: =F18+'Cash Flow Statement'!G19 -> 4136.3844 | H18: =G18+'Cash Flow Statement'!H19 -> 4136.3844
A19: Retained Earnings | B19: -375 | C19: -352.5 | D19: =C19+'Income Statement'!D17 -> -1341.5945 | E19: =D19+'Income Statement'!E17 -> -1855.2679 | F19: =E19+'Income Statement'!F17 -> -1717.8324 | G19: =F19+'Income Statement'!G17 -> -1090.0323 | H19: =G19+'Income Statement'!H17 -> -150.06514
A20: Total Equity | B20: =B18+B19 -> 1500 | C20: =C18+C19 -> 1982.5 | D20: =D18+D19 -> 1927.7161 | E20: =E18+E19 -> 2092.207 | F20: =F18+F19 -> 2418.552 | G20: =G18+G19 -> 3046.3521 | H20: =H18+H19 -> 3986.3192
A21: Total Liabilities & Equity | B21: =B16+B20 -> 3750 | C21: =C16+C20 -> 4592.5 | D21: =D16+D20 -> 4651.0627 | E21: =E16+E20 -> 4980.5773 | F21: =F16+F20 -> 5613.3039 | G21: =G16+G20 -> 6532.6313 | H21: =H16+H20 -> 7647.894
A22: Balance Check (should be 0) | B22: =B10-B21 -> 0 | C22: =C10-C21 -> 0
A23: Working Capital Metrics (added)
A24: DSO (days) = AR / Revenue x 365 | B24: =B6/'Income Statement'!B5*365 -> 36.5 | C24: =C6/'Income Statement'!C5*365 -> 36.5 | D24: =C24 -> 36.5 | E24: =D24 -> 36.5 | F24: =E24 -> 36.5 | G24: =F24 -> 36.5 | H24: =G24 -> 36.5
A25: DIO (days) = Inventory / COGS x 365 | B25: =B7/'Income Statement'!B7*365 -> 68.4375 | C25: =C7/'Income Statement'!C7*365 -> 73 | D25: =C25 -> 73 | E25: =D25 -> 73 | F25: =E25 -> 73 | G25: =F25 -> 73 | H25: =G25 -> 73
A26: DPO (days) = AP / COGS x 365 | B26: =B12/'Income Statement'!B7*365 -> 54.75 | C26: =C12/'Income Statement'!C7*365 -> 58.4 | D26: =C26 -> 58.4 | E26: =D26 -> 58.4 | F26: =E26 -> 58.4 | G26: =F26 -> 58.4 | H26: =G26 -> 58.4
A27: Net Working Capital ($mm) = AR + Inventory - AP | B27: =B6+B7-B12 -> 390 | C27: =C6+C7-C12 -> 585 | D27: =D6+D7-D12 -> 645.15739 | E27: =E6+E7-E12 -> 760.20668 | F27: =F6+F7-F12 -> 944.47417 | G27: =G6+G7-G12 -> 1115.1781 | H27: =H6+H7-H12 -> 1214.8172
A28: Increase / (Decrease) in NWC ($mm) | C28: =C27-B27 -> 195 | D28: =D27-C27 -> 60.157393 | E28: =E27-D27 -> 115.04928 | F28: =F27-E27 -> 184.26749 | G28: =G27-F27 -> 170.70396 | H28: =H27-G27 -> 99.639117

Sheet Cash Flow Statement
A1: VoltDrive Motors - EV Automobile Manufacturer
A2: Cash Flow Statement ($ in millions)
B3: FY2024A | C3: FY2025A | D3: FY2026E | E3: FY2027E | F3: FY2028E | G3: FY2029E | H3: FY2030E
A4: Operating Activities
A5: Net Income | B5: ='Income Statement'!B17 -> -285 | C5: ='Income Statement'!C17 -> 22.5 | D5: ='Income Statement'!D17 -> -989.09447 | E5: ='Income Statement'!E17 -> -513.67344 | F5: ='Income Statement'!F17 -> 137.43554 | G5: ='Income Statement'!G17 -> 627.80008 | H5: ='Income Statement'!H17 -> 939.96715
A6: Add: D&A | B6: ='Income Statement'!B12 -> 150 | C6: ='Income Statement'!C12 -> 200 | D6: ='Income Statement'!D12 -> 227.42857 | E6: ='Income Statement'!E12 -> 225.48922 | F6: ='Income Statement'!F12 -> 235.82626 | G6: ='Income Statement'!G12 -> 260.40983 | H6: ='Income Statement'!H12 -> 283.38045
A7: (Incr)/Decr in Accounts Receivable | C7: =-('Balance Sheet'!C6-'Balance Sheet'!B6) -> -150 | D7: =-('Balance Sheet'!D6-'Balance Sheet'!C6) -> -33.567568 | E7: =-('Balance Sheet'!E6-'Balance Sheet'!D6) -> -95.351351 | F7: =-('Balance Sheet'!F6-'Balance Sheet'!E6) -> -152.81757 | G7: =-('Balance Sheet'!G6-'Balance Sheet'!F6) -> -141.13703 | H7: =-('Balance Sheet'!H6-'Balance Sheet'!G6) -> -81.893189
A8: (Incr)/Decr in Inventory | C8: =-('Balance Sheet'!C7-'Balance Sheet'!B7) -> -225 | D8: =-('Balance Sheet'!D7-'Balance Sheet'!C7) -> -132.94913 | E8: =-('Balance Sheet'!E7-'Balance Sheet'!D7) -> -98.489666 | F8: =-('Balance Sheet'!F7-'Balance Sheet'!E7) -> -157.2496 | G8: =-('Balance Sheet'!G7-'Balance Sheet'!F7) -> -147.83466 | H8: =-('Balance Sheet'!H7-'Balance Sheet'!G7) -> -88.729641
A9: Incr/(Decr) in Accounts Payable | C9: ='Balance Sheet'!C12-'Balance Sheet'!B12 -> 180 | D9: ='Balance Sheet'!D12-'Balance Sheet'!C12 -> 106.3593 | E9: ='Balance Sheet'!E12-'Balance Sheet'!D12 -> 78.791733 | F9: ='Balance Sheet'!F12-'Balance Sheet'!E12 -> 125.79968 | G9: ='Balance Sheet'!G12-'Balance Sheet'!F12 -> 118.26773 | H9: ='Balance Sheet'!H12-'Balance Sheet'!G12 -> 70.983713
A10: Net Cash from Operating Activities | B10: =B5+B6 -> -135 | C10: =SUM(C5:C9) -> 27.5 | D10: =SUM(D5:D9) -> -821.82329 | E10: =SUM(E5:E9) -> -403.23351 | F10: =SUM(F5:F9) -> 188.99431 | G10: =SUM(G5:G9) -> 717.50596 | H10: =SUM(H5:H9) -> 1123.7085
A12: Investing Activities
A13: Capital Expenditures | B13: -500 | C13: -560 | D13: =-'Capacity Expansion'!C18 -> -201.97459 | E13: =-'Capacity Expansion'!D18 -> -361.16282 | F13: =-'Capacity Expansion'!E18 -> -558.4857 | G13: =-'Capacity Expansion'!F18 -> -561.8992 | H13: =-'Capacity Expansion'!G18 -> -441.32974
A14: Net Cash from Investing Activities | B14: =B13 -> -500 | C14: =C13 -> -560 | D14: =D13 -> -201.97459 | E14: =E13 -> -361.16282 | F14: =F13 -> -558.4857 | G14: =G13 -> -561.8992 | H14: =H13 -> -441.32974
A16: Financing Activities
A17: Debt Issued | B17: 700 | C17: 280 | D17: ='Debt Schedule'!C6+'Debt Schedule'!C13 -> 100.98729 | E17: ='Debt Schedule'!D6+'Debt Schedule'!D13 -> 180.58141 | F17: ='Debt Schedule'!E6+'Debt Schedule'!E13 -> 279.24285 | G17: ='Debt Schedule'!F6+'Debt Schedule'!F13 -> 280.9496 | H17: ='Debt Schedule'!G6+'Debt Schedule'!G13 -> 220.66487
A18: Debt Repaid | B18: -50 | C18: -100 | D18: ='Debt Schedule'!C7+'Debt Schedule'!C14 -> -94 | E18: ='Debt Schedule'!D7+'Debt Schedule'!D14 -> -94.349365 | F18: ='Debt Schedule'!E7+'Debt Schedule'!E14 -> -98.660967 | G18: ='Debt Schedule'!F7+'Debt Schedule'!F14 -> -107.69006 | H18: ='Debt Schedule'!G7+'Debt Schedule'!G14 -> -116.35304
A19: Equity Issued | B19: 1200 | C19: 460 | D19: =MAX(0,'Debt Schedule'!C25-(D23+D10+D14+D17+D18)) -> 934.31058 | E19: =MAX(0,'Debt Schedule'!D25-(E23+E10+E14+E17+E18)) -> 678.16428 | F19: =MAX(0,'Debt Schedule'!E25-(F23+F10+F14+F17+F18)) -> 188.90951 | G19: =MAX(0,'Debt Schedule'!F25-(G23+G10+G14+G17+G18)) -> 0 | H19: =MAX(0,'Debt Schedule'!G25-(H23+H10+H14+H17+H18)) -> 0
A20: Net Cash from Financing Activities | B20: =SUM(B17:B19) -> 1850 | C20: =SUM(C17:C19) -> 640 | D20: =SUM(D17:D19) -> 941.29788 | E20: =SUM(E17:E19) -> 764.39632 | F20: =SUM(F17:F19) -> 369.49139 | G20: =SUM(G17:G19) -> 173.25954 | H20: =SUM(H17:H19) -> 104.31183
A22: Net Change in Cash | B22: =B10+B14+B20 -> 1215 | C22: =C10+C14+C20 -> 107.5 | D22: =D10+D14+D20 -> -82.5 | E22: =E10+E14+E20 -> 0 | F22: =F10+F14+F20 -> 0 | G22: =G10+G14+G20 -> 328.8663 | H22: =H10+H14+H20 -> 786.69057
A23: Beginning Cash Balance | C23: ='Balance Sheet'!B5 -> 375 | D23: =C24 -> 482.5 | E23: =D24 -> 400 | F23: =E24 -> 400 | G23: =F24 -> 400 | H23: =G24 -> 728.8663
A24: Ending Cash Balance | B24: ='Balance Sheet'!B5 -> 375 | C24: =C23+C22 -> 482.5 | D24: =D23+D22 -> 400 | E24: =E23+E22 -> 400 | F24: =F23+F22 -> 400 | G24: =G23+G22 -> 728.8663 | H24: =H23+H22 -> 1515.5569
A25: Check vs. Balance Sheet Cash (should be 0) | C25: =C24-'Balance Sheet'!C5 -> 0 | D25: =D24-'Balance Sheet'!D5 -> 0 | E25: =E24-'Balance Sheet'!E5 -> 0 | F25: =F24-'Balance Sheet'!F5 -> 0 | G25: =G24-'Balance Sheet'!G5 -> 0 | H25: =H24-'Balance Sheet'!H5 -> 0

Sheet WACC
A1: VoltDrive Motors - WACC Calculation Template
A2: Fill in the yellow input cells and build the formulas in column B. Column D gives guidance only.
A3: Cost of Equity (CAPM)
A4: Risk-Free Rate (Rf) | B4: =Assumptions!B4 -> 0.0425
A5: Levered Beta | B5: =Assumptions!B5 -> 1.85
A6: Equity Market Risk Premium (Rm – Rf) | B6: =Assumptions!B6 -> 0.055
A7: Cost of Equity (Ke) | B7: =B4+(B5*B6) -> 0.14425
A9: Cost of Debt
A10: Pre-tax Cost of Debt (Kd) | B10: =Assumptions!B7 -> 0.075
A11: Marginal Tax Rate (t) | B11: =Assumptions!B8 -> 0.21
A12: After-tax Cost of Debt | B12: =B10*(1-B11) -> 0.05925
A14: Capital Structure (Market Value Weights)
A15: Market Value of Equity (E) | B15: =B24*B25 -> 3560
A16: Market Value of Debt (D) | B16: ='Balance Sheet'!C13+'Balance Sheet'!C15 -> 2070
A17: Total Capital (E + D) | B17: =B15+B16 -> 5630
A18: Weight of Equity (E / (E+D)) | B18: =B15/B17 -> 0.63232682
A19: Weight of Debt (D / (E+D)) | B19: =B16/B17 -> 0.36767318
A21: WACC | B21: =B18*B7+B19*B12 -> 0.11299778
A23: Equity Value Reference Inputs (ASSUMED - not given in brief)
A24: Diluted Shares Outstanding (mm) | B24: =Assumptions!B9 -> 400
A25: Reference Share Price ($) - proxy for latest funding round | B25: =Assumptions!B10 -> 8.9

Sheet DCF Valuation
A1: VoltDrive Motors - DCF Valuation
A2: $ in millions. Fill in every white cell below — no formulas are pre-built.
B3: FY2026E | C3: FY2027E | D3: FY2028E | E3: FY2029E | F3: FY2030E | G3: Terminal Year
A5: Revenue | B5: ='Income Statement'!D5 -> 4835.6757 | C5: ='Income Statement'!E5 -> 5789.1892 | D5: ='Income Statement'!F5 -> 7317.3649 | E5: ='Income Statement'!G5 -> 8728.7351 | F5: ='Income Statement'!H5 -> 9547.667 | G5: =F5*(1+$B$24) -> 9786.3587
A6: Revenue Growth % | B6: ='Income Statement'!D6 -> 0.074594595 | C6: ='Income Statement'!E6 -> 0.1971831 | D6: ='Income Statement'!F6 -> 0.26397059 | E6: ='Income Statement'!G6 -> 0.19287958 | F6: ='Income Statement'!H6 -> 0.093820225 | G6: =$B$24 -> 0.025
A7: EBITDA | B7: ='Income Statement'!D11 -> -606.4159 | C7: ='Income Statement'!E11 -> -132.41017 | D7: ='Income Statement'!F11 -> 572.03674 | E7: ='Income Statement'!G11 -> 1230.8786 | F7: ='Income Statement'!H11 -> 1661.9918 | G7: =F7*(1+$B$24) -> 1703.5416
A8: EBITDA Margin % | B8: =B7/B5 -> -0.12540458 | C8: =C7/C5 -> -0.022871972 | D8: =D7/D5 -> 0.078175239 | E8: =E7/E5 -> 0.14101454 | F8: =F7/F5 -> 0.17407308 | G8: =G7/G5 -> 0.17407308
A9: Less: D&A | B9: =-'Income Statement'!D12 -> -227.42857 | C9: =-'Income Statement'!E12 -> -225.48922 | D9: =-'Income Statement'!F12 -> -235.82626 | E9: =-'Income Statement'!G12 -> -260.40983 | F9: =-'Income Statement'!H12 -> -283.38045 | G9: =F9*(1+B24) -> -290.46496
A10: EBIT | B10: =B7+B9 -> -833.84447 | C10: =C7+C9 -> -357.8994 | D10: =D7+D9 -> 336.21049 | E10: =E7+E9 -> 970.46874 | F10: =F7+F9 -> 1378.6114 | G10: =G7+G9 -> 1413.0767
A11: Less: Taxes on EBIT | B11: =-B10*WACC!$B$11 -> 175.10734 | C11: =-C10*WACC!$B$11 -> 75.158873 | D11: =-D10*WACC!$B$11 -> -70.604203 | E11: =-E10*WACC!$B$11 -> -203.79844 | F11: =-F10*WACC!$B$11 -> -289.50839 | G11: =F11*(1+$B$24) -> -296.7461
A12: EBIAT (NOPAT) | B12: =B10+B11 -> -658.73713 | C12: =C10+C11 -> -282.74052 | D12: =D10+D11 -> 265.60629 | E12: =E10+E11 -> 766.67031 | F12: =F10+F11 -> 1089.103 | G12: =G10+G11 -> 1116.3306
A13: Add: D&A | B13: ='Income Statement'!D12 -> 227.42857 | C13: ='Income Statement'!E12 -> 225.48922 | D13: ='Income Statement'!F12 -> 235.82626 | E13: ='Income Statement'!G12 -> 260.40983 | F13: ='Income Statement'!H12 -> 283.38045 | G13: =F13*(1+B24) -> 290.46496
A14: Less: Capital Expenditures | B14: =-'Capacity Expansion'!C18 -> -201.97459 | C14: =-'Capacity Expansion'!D18 -> -361.16282 | D14: =-'Capacity Expansion'!E18 -> -558.4857 | E14: =-'Capacity Expansion'!F18 -> -561.8992 | F14: =-'Capacity Expansion'!G18 -> -441.32974 | G14: =F14*(1+B24) -> -452.36298
A15: Less: Increase in Net Working Capital | B15: =-'Balance Sheet'!D28 -> -60.157393 | C15: =-'Balance Sheet'!E28 -> -115.04928 | D15: =-'Balance Sheet'!F28 -> -184.26749 | E15: =-'Balance Sheet'!G28 -> -170.70396 | F15: =-'Balance Sheet'!H28 -> -99.639117 | G15: =F15*(1+B24) -> -102.1301
A16: Unlevered Free Cash Flow | B16: =B12+B13+B14+B15 -> -693.44054 | C16: =C12+C13+C14+C15 -> -533.4634 | D16: =D12+D13+D14+D15 -> -241.32064 | E16: =E12+E13+E14+E15 -> 294.47698 | F16: =F12+F13+F14+F15 -> 831.51459 | G16: =G12+G13+G14+G15 -> 852.30246
A18: Discount Period | B18: 1 | C18: 2 | D18: 3 | E18: 4 | F18: 5
A19: Discount Factor | B19: =1/(1+$B$25)^B18 -> 0.89847439 | C19: =1/(1+$B$25)^C18 -> 0.80725623 | D19: =1/(1+$B$25)^D18 -> 0.72529905 | E19: =1/(1+$B$25)^E18 -> 0.65166262 | F19: =1/(1+$B$25)^F18 -> 0.58550217
A20: PV of Unlevered FCF | B20: =B16*B19 -> -623.03857 | C20: =C16*C19 -> -430.64165 | D20: =D16*D19 -> -175.02963 | E20: =E16*E19 -> 191.89964 | F20: =F16*F19 -> 486.8536
A22: Valuation Summary
A23: Sum of PV of Explicit-Period FCF | B23: =SUM(B20:F20) -> -549.95661
A24: Terminal Growth Rate (g) | B24: =Assumptions!B11 -> 0.025
A25: WACC (from WACC tab) | B25: =WACC!B21 -> 0.11299778
A26: Terminal Value (Gordon Growth) | B26: =F16*(1+B24)/(B25-B24) -> 9685.4996
A27: PV of Terminal Value | B27: =B26/(1+B25)^F18 -> 5670.881
A28: Enterprise Value | B28: =B23+B27 -> 5120.9244
A29: Less: Total Debt | B29: =-'Debt Schedule'!B19 -> -2070
A30: Add: Cash & Equivalents | B30: ='Debt Schedule'!B21 -> 482.5
A31: Equity Value | B31: =B28+B29+B30 -> 3533.4244
A32: Diluted Shares Outstanding | B32: =WACC!B24 -> 400
A33: Implied Value per Share | B33: =B31/B32 -> 8.833561

Sheet Revenue & Cost Drivers
A1: VoltDrive Motors - Revenue & Cost Drivers Template
A2: Build volume, price, and unit-cost drivers here, then feed the results into the DCF tab.
B3: FY2025A | C3: FY2026E | D3: FY2027E | E3: FY2028E | F3: FY2029E | G3: FY2030E
A4: Revenue Drivers
A5: Vehicles Sold (units, '000) | B5: =B9/B7 -> 59.618442 | C5: =B5*(1+C6) -> 66.772655 | D5: =C5*(1+D6) -> 83.465819 | E5: =D5*(1+E6) -> 112.67886 | F5: =E5*(1+F6) -> 144.22893 | G5: =F5*(1+G6) -> 170.19014
A6: Unit Growth % | C6: =Assumptions!C13 -> 0.12 | D6: =Assumptions!D13 -> 0.25 | E6: =Assumptions!E13 -> 0.35 | F6: =Assumptions!F13 -> 0.28 | G6: =Assumptions!G13 -> 0.18
A7: Average Selling Price (ASP, $'000/unit) | B7: 74 | C7: =B7+(D7-B7)/2 -> 71 | D7: =Assumptions!D14 -> 68 | E7: =D7+($G$7-$D$7)/3 -> 63.666667 | F7: =E7+($G$7-$D$7)/3 -> 59.333333 | G7: =Assumptions!G14 -> 55
A8: ASP Growth % | C8: =C7/B7-1 -> -0.040540541 | D8: =D7/C7-1 -> -0.042253521 | E8: =E7/D7-1 -> -0.06372549 | F8: =F7/E7-1 -> -0.068062827 | G8: =G7/F7-1 -> -0.073033708
A9: Revenue from Vehicle Sales ($mm) | B9: ='Income Statement'!C5/(1+'Revenue & Cost Drivers'!B23) -> 4411.7647 | C9: =C5*C7 -> 4740.8585 | D9: =D5*D7 -> 5675.6757 | E9: =E5*E7 -> 7173.8871 | F9: =F5*F7 -> 8557.5835 | G9: =G5*G7 -> 9360.4579
A10: Other Revenue (services, software, energy) ($mm) | B10: =B9*B23 -> 88.235294 | C10: =C9*C23 -> 94.81717 | D10: =D9*D23 -> 113.51351 | E10: =E9*E23 -> 143.47774 | F10: =F9*F23 -> 171.15167 | G10: =G9*G23 -> 187.20916
A11: Total Revenue ($mm) | B11: =B9+B10 -> 4500 | C11: =C9+C10 -> 4835.6757 | D11: =D9+D10 -> 5789.1892 | E11: =E9+E10 -> 7317.3649 | F11: =F9+F10 -> 8728.7351 | G11: =G9+G10 -> 9547.667
A12: Cost Drivers
A13: Battery Cost per Unit ($'000) | B13: =Assumptions!B17 -> 21 | C13: =Assumptions!C17 -> 18.5 | D13: =Assumptions!D17 -> 15.8 | E13: =Assumptions!E17 -> 13.2 | F13: =Assumptions!F17 -> 11.5 | G13: =Assumptions!G17 -> 10.2
A14: Other Materials/Assembly Cost per Unit ($'000) | B14: =Assumptions!B18 -> 45 | C14: =Assumptions!C18 -> 42 | D14: =Assumptions!D18 -> 38.5 | E14: =Assumptions!E18 -> 34 | F14: =Assumptions!F18 -> 30.5 | G14: =Assumptions!G18 -> 28
A15: Total Variable Cost per Unit ($'000) | B15: =B13+B14 -> 66 | C15: =C13+C14 -> 60.5 | D15: =D13+D14 -> 54.3 | E15: =E13+E14 -> 47.2 | F15: =F13+F14 -> 42 | G15: =G13+G14 -> 38.2
A16: COGS ($mm) | B16: ='Income Statement'!C7 -> 3375 | C16: =C5*C15 -> 4039.7456 | D16: =D5*D15 -> 4532.194 | E16: =E5*E15 -> 5318.442 | F16: =F5*F15 -> 6057.6153 | G16: =G5*G15 -> 6501.2635
A17: Gross Margin % | B17: =(B11-B16)/B11 -> 0.25 | C17: =(C11-C16)/C11 -> 0.16459542 | D17: =(D11-D16)/D11 -> 0.21712803 | E17: =(E11-E16)/E11 -> 0.27317524 | F17: =(F11-F16)/F11 -> 0.30601454 | G17: =(G11-G16)/G11 -> 0.31907308
A18: R&D as % of Revenue | B18: ='Income Statement'!C9/'Revenue & Cost Drivers'!B11 -> 0.08 | C18: =Assumptions!C20 -> 0.14 | D18: =Assumptions!D20 -> 0.115 | E18: =Assumptions!E20 -> 0.09 | F18: =Assumptions!F20 -> 0.075 | G18: =Assumptions!G20 -> 0.065
A19: R&D Expense ($mm) | B19: ='Income Statement'!C9 -> 360 | C19: =C11*C18 -> 676.99459 | D19: =D11*D18 -> 665.75676 | E19: =E11*E18 -> 658.56284 | F19: =F11*F18 -> 654.65514 | G19: =G11*G18 -> 620.59836
A20: SG&A as % of Revenue | B20: ='Income Statement'!C10/'Revenue & Cost Drivers'!B11 -> 0.1 | C20: =Assumptions!C21 -> 0.15 | D20: =Assumptions!D21 -> 0.125 | E20: =Assumptions!E21 -> 0.105 | F20: =Assumptions!F21 -> 0.09 | G20: =Assumptions!G21 -> 0.08
A21: SG&A Expense ($mm) | B21: ='Income Statement'!C10 -> 450 | C21: =C11*C20 -> 725.35135 | D21: =D11*D20 -> 723.64865 | E21: =E11*E20 -> 768.32331 | F21: =F11*F20 -> 785.58616 | G21: =G11*G20 -> 763.81336
A22: Additional Assumptions & Reconciliation (added)
A23: Other Revenue as % of Vehicle Sales Revenue | B23: =Assumptions!$B$15 -> 0.02 | C23: =Assumptions!$B$15 -> 0.02 | D23: =Assumptions!$B$15 -> 0.02 | E23: =Assumptions!$B$15 -> 0.02 | F23: =Assumptions!$B$15 -> 0.02 | G23: =Assumptions!$B$15 -> 0.02
A24: FY25A implied units back-solved: (Reported Revenue / (1 + Other %)) / ASP
A25: FY25A COGS implied by unit-cost drivers ($mm) = Units x $66.0k | B25: =B5*B15 -> 3934.8172
A26: FY25A variance: driver-implied COGS less reported COGS ($mm) | B26: =B25-B16 -> 559.81717

Sheet Capacity Expansion
A1: VoltDrive Motors - Capacity Expansion Template
A2: Link required capacity to unit sales from the Revenue & Cost Drivers tab, then size capex to close any capacity gap.
B3: FY2025A | C3: FY2026E | D3: FY2027E | E3: FY2028E | F3: FY2029E | G3: FY2030E
A4: Demand Side
A5: Required Units Sold (from Drivers tab, '000) | B5: ='Revenue & Cost Drivers'!B5 -> 59.618442 | C5: ='Revenue & Cost Drivers'!C5 -> 66.772655 | D5: ='Revenue & Cost Drivers'!D5 -> 83.465819 | E5: ='Revenue & Cost Drivers'!E5 -> 112.67886 | F5: ='Revenue & Cost Drivers'!F5 -> 144.22893 | G5: ='Revenue & Cost Drivers'!G5 -> 170.19014
A6: Required Annual Capacity (units, '000) | B6: =B5/B7 -> 100 | C6: =C5/C7 -> 102.72716 | D6: =D5/D7 -> 117.14501 | E6: =E5/E7 -> 145.39207 | F6: =F5/F7 -> 172.21365 | G6: =G5/G7 -> 189.10016
A7: Utilization Target % | B7: =B5/B12 -> 0.59618442 | C7: =Assumptions!C24 -> 0.65 | D7: =C7+($G$7-$C$7)/4 -> 0.7125 | E7: =D7+($G$7-$C$7)/4 -> 0.775 | F7: =E7+($G$7-$C$7)/4 -> 0.8375 | G7: =Assumptions!G24 -> 0.9
A8: Supply Side
A9: Existing Installed Capacity, Beginning (units, '000) | C9: =B12 -> 100 | D9: =C12 -> 102.72716 | E9: =D12 -> 117.14501 | F9: =E12 -> 145.39207 | G9: =F12 -> 172.21365
A10: Capacity Gap (Required – Existing) | C10: =MAX(0,C6-C9) -> 2.7271616 | D10: =MAX(0,D6-D9) -> 14.417847 | E10: =MAX(0,E6-E9) -> 28.247063 | F10: =MAX(0,F6-F9) -> 26.821582 | G10: =MAX(0,G6-G9) -> 16.886505
A11: New Capacity to be Added (units, '000) | C11: =C10 -> 2.7271616 | D11: =D10 -> 14.417847 | E11: =E10 -> 28.247063 | F11: =F10 -> 26.821582 | G11: =G10 -> 16.886505
A12: Installed Capacity, Ending (units, '000) | B12: =Assumptions!$B$23 -> 100 | C12: =C9+C11 -> 102.72716 | D12: =D9+D11 -> 117.14501 | E12: =E9+E11 -> 145.39207 | F12: =F9+F11 -> 172.21365 | G12: =G9+G11 -> 189.10016
A14: Capex Sizing
A15: Capex per Unit of New Capacity ($mm per '000 units) | C15: =Assumptions!$B$25 -> 12 | D15: =Assumptions!$B$25 -> 12 | E15: =Assumptions!$B$25 -> 12 | F15: =Assumptions!$B$25 -> 12 | G15: =Assumptions!$B$25 -> 12
A16: Growth / Expansion Capex ($mm) | C16: =C11*C15 -> 32.725939 | D16: =D11*D15 -> 173.01417 | E16: =E11*E15 -> 338.96475 | F16: =F11*F15 -> 321.85899 | G16: =G11*G15 -> 202.63807
A17: Maintenance Capex ($mm) | C17: ='Revenue & Cost Drivers'!C11*C28 -> 169.24865 | D17: ='Revenue & Cost Drivers'!D11*D28 -> 188.14865 | E17: ='Revenue & Cost Drivers'!E11*E28 -> 219.52095 | F17: ='Revenue & Cost Drivers'!F11*F28 -> 240.04022 | G17: ='Revenue & Cost Drivers'!G11*G28 -> 238.69168
A18: Total Capex ($mm) | B18: =-'Cash Flow Statement'!C13 -> 560 | C18: =C16+C17 -> 201.97459 | D18: =D16+D17 -> 361.16282 | E18: =E16+E17 -> 558.4857 | F18: =F16+F17 -> 561.8992 | G18: =G16+G17 -> 441.32974
A20: PP&E Roll-forward
A21: Net PP&E, Beginning ($mm) | B21: ='Balance Sheet'!B9 -> 2625 | C21: =B24 -> 2985 | D21: =C24 -> 2959.546 | E21: =D24 -> 3095.2196 | F21: =E24 -> 3417.8791 | G21: =F24 -> 3719.3684
A22: Add: Total Capex ($mm) | B22: =B18 -> 560 | C22: =C18 -> 201.97459 | D22: =D18 -> 361.16282 | E22: =E18 -> 558.4857 | F22: =F18 -> 561.8992 | G22: =G18 -> 441.32974
A23: Less: D&A ($mm) | B23: ='Income Statement'!C12 -> 200 | C23: =C21*C29 -> 227.42857 | D23: =D21*D29 -> 225.48922 | E23: =E21*E29 -> 235.82626 | F23: =F21*F29 -> 260.40983 | G23: =G21*G29 -> 283.38045
A24: Net PP&E, Ending ($mm) | B24: =B21+B22-B23 -> 2985 | C24: =C21+C22-C23 -> 2959.546 | D24: =D21+D22-D23 -> 3095.2196 | E24: =E21+E22-E23 -> 3417.8791 | F24: =F21+F22-F23 -> 3719.3684 | G24: =G21+G22-G23 -> 3877.3177
A25: Additional Assumptions & Reconciliation (added)
A26: Other Revenue as % of Vehicle Sales Revenue
A27: FY25A implied units back-solved: (Reported Revenue / (1 + Other %)) / ASP
A28: FY25A COGS implied by unit-cost drivers ($mm) = Units x $66.0k | C28: =Assumptions!C26 -> 0.035 | D28: =C28+($G$28-$C$28)/4 -> 0.0325 | E28: =D28+($G$28-$C$28)/4 -> 0.03 | F28: =E28+($G$28-$C$28)/4 -> 0.0275 | G28: =Assumptions!G26 -> 0.025
A29: FY25A variance: driver-implied COGS less reported COGS ($mm) | B29: ='Income Statement'!C12/'Balance Sheet'!B9 -> 0.076190476 | C29: =B29 -> 0.076190476 | D29: =C29 -> 0.076190476 | E29: =D29 -> 0.076190476 | F29: =E29 -> 0.076190476 | G29: =F29 -> 0.076190476

Sheet Debt Schedule
A1: VoltDrive Motors - Debt Schedule Template
A2: Build opening/closing balances, draws, and interest for each tranche; link interest expense back to the Income Statement.
B3: FY2025A | C3: FY2026E | D3: FY2027E | E3: FY2028E | F3: FY2029E | G3: FY2030E
A4: Short-Term Debt / Revolver
A5: Beginning Balance | B5: ='Balance Sheet'!B13 -> 190 | C5: =B8 -> 190 | D5: =C8 -> 190 | E5: =D8 -> 190 | F5: =E8 -> 190 | G5: =F8 -> 190
A6: Draws | C6: =Assumptions!$B$28 -> 0 | D6: =Assumptions!$B$28 -> 0 | E6: =Assumptions!$B$28 -> 0 | F6: =Assumptions!$B$28 -> 0 | G6: =Assumptions!$B$28 -> 0
A7: Repayments | C7: =Assumptions!$B$29 -> 0 | D7: =Assumptions!$B$29 -> 0 | E7: =Assumptions!$B$29 -> 0 | F7: =Assumptions!$B$29 -> 0 | G7: =Assumptions!$B$29 -> 0
A8: Ending Balance | B8: ='Balance Sheet'!C13 -> 190 | C8: =C5+C6+C7 -> 190 | D8: =D5+D6+D7 -> 190 | E8: =E5+E6+E7 -> 190 | F8: =F5+F6+F7 -> 190 | G8: =G5+G6+G7 -> 190
A9: Interest Rate % | C9: =WACC!$B$10 -> 0.075 | D9: =WACC!$B$10 -> 0.075 | E9: =WACC!$B$10 -> 0.075 | F9: =WACC!$B$10 -> 0.075 | G9: =WACC!$B$10 -> 0.075
A10: Interest Expense | C10: =C5*C9 -> 14.25 | D10: =D5*D9 -> 14.25 | E10: =E5*E9 -> 14.25 | F10: =F5*F9 -> 14.25 | G10: =G5*G9 -> 14.25
A11: Long-Term Debt / Term Loan
A12: Beginning Balance | B12: ='Balance Sheet'!B15 -> 1700 | C12: =B15 -> 1880 | D12: =C15 -> 1886.9873 | E12: =D15 -> 1973.2193 | F12: =E15 -> 2153.8012 | G12: =F15 -> 2327.0608
A13: New Issuance (funds capex/expansion) | B13: ='Cash Flow Statement'!C17 -> 280 | C13: =C23*'Capacity Expansion'!C18 -> 100.98729 | D13: =D23*'Capacity Expansion'!D18 -> 180.58141 | E13: =E23*'Capacity Expansion'!E18 -> 279.24285 | F13: =F23*'Capacity Expansion'!F18 -> 280.9496 | G13: =G23*'Capacity Expansion'!G18 -> 220.66487
A14: Scheduled Repayments | B14: ='Cash Flow Statement'!C18 -> -100 | C14: =-C24*C12 -> -94 | D14: =-D24*D12 -> -94.349365 | E14: =-E24*E12 -> -98.660967 | F14: =-F24*F12 -> -107.69006 | G14: =-G24*G12 -> -116.35304
A15: Ending Balance | B15: =B12+B13+B14 -> 1880 | C15: =C12+C13+C14 -> 1886.9873 | D15: =D12+D13+D14 -> 1973.2193 | E15: =E12+E13+E14 -> 2153.8012 | F15: =F12+F13+F14 -> 2327.0608 | G15: =G12+G13+G14 -> 2431.3726
A16: Interest Rate % | C16: =WACC!$B$10 -> 0.075 | D16: =WACC!$B$10 -> 0.075 | E16: =WACC!$B$10 -> 0.075 | F16: =WACC!$B$10 -> 0.075 | G16: =WACC!$B$10 -> 0.075
A17: Interest Expense | C17: =C12*C16 -> 141 | D17: =D12*D16 -> 141.52405 | E17: =E12*E16 -> 147.99145 | F17: =F12*F16 -> 161.53509 | G17: =G12*G16 -> 174.52956
A18: Total Debt Summary
A19: Total Debt, Ending Balance | B19: =B8+B15 -> 2070 | C19: =C8+C15 -> 2076.9873 | D19: =D8+D15 -> 2163.2193 | E19: =E8+E15 -> 2343.8012 | F19: =F8+F15 -> 2517.0608 | G19: =G8+G15 -> 2621.3726
A20: Total Interest Expense | B20: ='Income Statement'!C14 -> 85 | C20: =C10+C17 -> 155.25 | D20: =D10+D17 -> 155.77405 | E20: =E10+E17 -> 162.24145 | F20: =F10+F17 -> 175.78509 | G20: =G10+G17 -> 188.77956
A21: Cash Balance (min cash / sweep check) | B21: ='Balance Sheet'!C5 -> 482.5 | C21: ='Balance Sheet'!D5 -> 400 | D21: ='Balance Sheet'!E5 -> 400 | E21: ='Balance Sheet'!F5 -> 400 | F21: ='Balance Sheet'!G5 -> 728.8663 | G21: ='Balance Sheet'!H5 -> 1515.5569
A22: Additional Assumptions (added)
A23: New LT Debt as % of Total Capex | C23: =Assumptions!$B$30 -> 0.5 | D23: =Assumptions!$B$30 -> 0.5 | E23: =Assumptions!$B$30 -> 0.5 | F23: =Assumptions!$B$30 -> 0.5 | G23: =Assumptions!$B$30 -> 0.5
A24: Scheduled LT Repayment (% of Beginning LT Balance) | C24: =Assumptions!$B$31 -> 0.05 | D24: =Assumptions!$B$31 -> 0.05 | E24: =Assumptions!$B$31 -> 0.05 | F24: =Assumptions!$B$31 -> 0.05 | G24: =Assumptions!$B$31 -> 0.05
A25: Minimum Cash Balance ($mm) - shortfall funded by equity issuance (CFS row 20) | C25: =Assumptions!$B$32 -> 400 | D25: =Assumptions!$B$32 -> 400 | E25: =Assumptions!$B$32 -> 400 | F25: =Assumptions!$B$32 -> 400 | G25: =Assumptions!$B$32 -> 400
